Metadata-Version: 2.1
Name: tk-dragtool
Version: 1.1.4
Summary: 提供用鼠标拖动、缩放tkinter控件工具的跨平台模块。A cross-platform module providing tools to dragand resize tkinter windows and widgets with the mouse.
Home-page: https://github.com/qfcy/Python/blob/main/tk_dragtool.py
Author: qfcy
Author-email: 3076711200@qq.com
Keywords: tkinter,drag,tool
Classifier: Programming Language :: Python
Classifier: Natural Language :: Chinese (Simplified)
Classifier: Topic :: Software Development :: User Interfaces
Classifier: Topic :: Desktop Environment
License-File: LICENSE
